nc_time_axis/__init__.py
nc_time_axis/_matplotlib_compatibility.py
nc_time_axis/_version.py
nc_time_axis/tests/__init__.py
nc_time_axis/tests/integration/__init__.py
nc_time_axis/tests/integration/test_plot.py
nc_time_axis/tests/unit/__init__.py
nc_time_axis/tests/unit/test_AutoCFTimeFormatter.py
nc_time_axis/tests/unit/test_CFTimeFormatter.py
nc_time_axis/tests/unit/test_CalendarDateTime.py
nc_time_axis/tests/unit/test_NetCDFTimeConverter.py
nc_time_axis/tests/unit/test_NetCDFTimeDateLocator.py
nc_time_axis-1.4.1.dist-info/LICENSE
nc_time_axis-1.4.1.dist-info/METADATA
nc_time_axis-1.4.1.dist-info/WHEEL
nc_time_axis-1.4.1.dist-info/top_level.txt
nc_time_axis-1.4.1.dist-info/RECORD
