Metadata-Version: 2.1
Name: nc-time-axis
Version: 1.4.1
Summary: Provides support for a cftime axis in matplotlib
Home-page: https://github.com/SciTools/nc-time-axis
Author: SciTools Developers
License: BSD 3-Clause
Download-URL: https://github.com/SciTools/nc-time-axis
Project-URL: Code, https://github.com/SciTools/nc-time-axis
Project-URL: Discussions, https://github.com/SciTools/nc-time-axis/discussions
Project-URL: Issues, https://github.com/SciTools/nc-time-axis/issues
Keywords: axis,cftime,matplotlib
Platform: UNKNOWN
Classifier: Development Status :: 5 - Production/Stable
Classifier: Intended Audience :: Science/Research
Classifier: License :: OSI Approved :: BSD License
Classifier: Operating System :: MacOS
Classifier: Operating System :: Microsoft :: Windows
Classifier: Operating System :: POSIX :: Linux
Classifier: Operating System :: Unix
Classifier: Programming Language :: Python :: 3 :: Only
Classifier: Programming Language :: Python :: 3.7
Classifier: Programming Language :: Python :: 3.8
Classifier: Programming Language :: Python :: 3.9
Classifier: Topic :: Scientific/Engineering
Requires-Python: >=3.7
Provides-Extra: docs
Provides-Extra: test
Provides-Extra: all
License-File: LICENSE
